[
  {
    "type": "constructor",
    "inputs": [
      {
        "name": "implementationAuthority",
        "type": "address",
        "internalType": "address"
      }
    ],
    "stateMutability": "nonpayable"
  },
  {
    "type": "function",
    "name": "addTokenFactory",
    "inputs": [
      {
        "name": "_factory",
        "type": "address",
        "internalType": "address"
      }
    ],
    "outputs": [],
    "stateMutability": "nonpayable"
  },
  {
    "type": "function",
    "name": "createIdentity",
    "inputs": [
      {
        "name": "_wallet",
        "type": "address",
        "internalType": "address"
      },
      {
        "name": "_salt",
        "type": "string",
        "internalType": "string"
      }
    ],
    "outputs": [
      {
        "name": "",
        "type": "address",
        "internalType": "address"
      }
    ],
    "stateMutability": "nonpayable"
  },
  {
    "type": "function",
    "name": "createIdentityWithManagementKeys",
    "inputs": [
      {
        "name": "_wallet",
        "type": "address",
        "internalType": "address"
      },
      {
        "name": "_salt",
        "type": "string",
        "internalType": "string"
      },
      {
        "name": "_managementKeys",
        "type": "bytes32[]",
        "internalType": "bytes32[]"
      }
    ],
    "outputs": [
      {
        "name": "",
        "type": "address",
        "internalType": "address"
      }
    ],
    "stateMutability": "nonpayable"
  },
  {
    "type": "function",
    "name": "createTokenIdentity",
    "inputs": [
      {
        "name": "_token",
        "type": "address",
        "internalType": "address"
      },
      {
        "name": "_tokenOwner",
        "type": "address",
        "internalType": "address"
      },
      {
        "name": "_salt",
        "type": "string",
        "internalType": "string"
      }
    ],
    "outputs": [
      {
        "name": "",
        "type": "address",
        "internalType": "address"
      }
    ],
    "stateMutability": "nonpayable"
  },
  {
    "type": "function",
    "name": "getIdentity",
    "inputs": [
      {
        "name": "_wallet",
        "type": "address",
        "internalType": "address"
      }
    ],
    "outputs": [
      {
        "name": "",
        "type": "address",
        "internalType": "address"
      }
    ],
    "stateMutability": "view"
  },
  {
    "type": "function",
    "name": "getToken",
    "inputs": [
      {
        "name": "_identity",
        "type": "address",
        "internalType": "address"
      }
    ],
    "outputs": [
      {
        "name": "",
        "type": "address",
        "internalType": "address"
      }
    ],
    "stateMutability": "view"
  },
  {
    "type": "function",
    "name": "getWallets",
    "inputs": [
      {
        "name": "_identity",
        "type": "address",
        "internalType": "address"
      }
    ],
    "outputs": [
      {
        "name": "",
        "type": "address[]",
        "internalType": "address[]"
      }
    ],
    "stateMutability": "view"
  },
  {
    "type": "function",
    "name": "implementationAuthority",
    "inputs": [],
    "outputs": [
      {
        "name": "",
        "type": "address",
        "internalType": "address"
      }
    ],
    "stateMutability": "view"
  },
  {
    "type": "function",
    "name": "isSaltTaken",
    "inputs": [
      {
        "name": "_salt",
        "type": "string",
        "internalType": "string"
      }
    ],
    "outputs": [
      {
        "name": "",
        "type": "bool",
        "internalType": "bool"
      }
    ],
    "stateMutability": "view"
  },
  {
    "type": "function",
    "name": "isTokenFactory",
    "inputs": [
      {
        "name": "_factory",
        "type": "address",
        "internalType": "address"
      }
    ],
    "outputs": [
      {
        "name": "",
        "type": "bool",
        "internalType": "bool"
      }
    ],
    "stateMutability": "view"
  },
  {
    "type": "function",
    "name": "linkWallet",
    "inputs": [
      {
        "name": "_newWallet",
        "type": "address",
        "internalType": "address"
      }
    ],
    "outputs": [],
    "stateMutability": "nonpayable"
  },
  {
    "type": "function",
    "name": "owner",
    "inputs": [],
    "outputs": [
      {
        "name": "",
        "type": "address",
        "internalType": "address"
      }
    ],
    "stateMutability": "view"
  },
  {
    "type": "function",
    "name": "removeTokenFactory",
    "inputs": [
      {
        "name": "_factory",
        "type": "address",
        "internalType": "address"
      }
    ],
    "outputs": [],
    "stateMutability": "nonpayable"
  },
  {
    "type": "function",
    "name": "renounceOwnership",
    "inputs": [],
    "outputs": [],
    "stateMutability": "nonpayable"
  },
  {
    "type": "function",
    "name": "transferOwnership",
    "inputs": [
      {
        "name": "newOwner",
        "type": "address",
        "internalType": "address"
      }
    ],
    "outputs": [],
    "stateMutability": "nonpayable"
  },
  {
    "type": "function",
    "name": "unlinkWallet",
    "inputs": [
      {
        "name": "_oldWallet",
        "type": "address",
        "internalType": "address"
      }
    ],
    "outputs": [],
    "stateMutability": "nonpayable"
  },
  {
    "type": "event",
    "name": "Deployed",
    "inputs": [
      {
        "name": "_addr",
        "type": "address",
        "indexed": true,
        "internalType": "address"
      }
    ],
    "anonymous": false
  },
  {
    "type": "event",
    "name": "OwnershipTransferred",
    "inputs": [
      {
        "name": "previousOwner",
        "type": "address",
        "indexed": true,
        "internalType": "address"
      },
      {
        "name": "newOwner",
        "type": "address",
        "indexed": true,
        "internalType": "address"
      }
    ],
    "anonymous": false
  },
  {
    "type": "event",
    "name": "TokenFactoryAdded",
    "inputs": [
      {
        "name": "factory",
        "type": "address",
        "indexed": true,
        "internalType": "address"
      }
    ],
    "anonymous": false
  },
  {
    "type": "event",
    "name": "TokenFactoryRemoved",
    "inputs": [
      {
        "name": "factory",
        "type": "address",
        "indexed": true,
        "internalType": "address"
      }
    ],
    "anonymous": false
  },
  {
    "type": "event",
    "name": "TokenLinked",
    "inputs": [
      {
        "name": "token",
        "type": "address",
        "indexed": true,
        "internalType": "address"
      },
      {
        "name": "identity",
        "type": "address",
        "indexed": true,
        "internalType": "address"
      }
    ],
    "anonymous": false
  },
  {
    "type": "event",
    "name": "WalletLinked",
    "inputs": [
      {
        "name": "wallet",
        "type": "address",
        "indexed": true,
        "internalType": "address"
      },
      {
        "name": "identity",
        "type": "address",
        "indexed": true,
        "internalType": "address"
      }
    ],
    "anonymous": false
  },
  {
    "type": "event",
    "name": "WalletUnlinked",
    "inputs": [
      {
        "name": "wallet",
        "type": "address",
        "indexed": true,
        "internalType": "address"
      },
      {
        "name": "identity",
        "type": "address",
        "indexed": true,
        "internalType": "address"
      }
    ],
    "anonymous": false
  }
]
