[
  {
    "type": "function",
    "name": "addIdentityToStorage",
    "inputs": [
      {
        "name": "_userAddress",
        "type": "address",
        "internalType": "address"
      },
      {
        "name": "_identity",
        "type": "address",
        "internalType": "contract IIdentity"
      },
      {
        "name": "_country",
        "type": "uint16",
        "internalType": "uint16"
      }
    ],
    "outputs": [],
    "stateMutability": "nonpayable"
  },
  {
    "type": "function",
    "name": "bindIdentityRegistry",
    "inputs": [
      {
        "name": "_identityRegistry",
        "type": "address",
        "internalType": "address"
      }
    ],
    "outputs": [],
    "stateMutability": "nonpayable"
  },
  {
    "type": "function",
    "name": "linkedIdentityRegistries",
    "inputs": [],
    "outputs": [
      {
        "name": "",
        "type": "address[]",
        "internalType": "address[]"
      }
    ],
    "stateMutability": "view"
  },
  {
    "type": "function",
    "name": "modifyStoredIdentity",
    "inputs": [
      {
        "name": "_userAddress",
        "type": "address",
        "internalType": "address"
      },
      {
        "name": "_identity",
        "type": "address",
        "internalType": "contract IIdentity"
      }
    ],
    "outputs": [],
    "stateMutability": "nonpayable"
  },
  {
    "type": "function",
    "name": "modifyStoredInvestorCountry",
    "inputs": [
      {
        "name": "_userAddress",
        "type": "address",
        "internalType": "address"
      },
      {
        "name": "_country",
        "type": "uint16",
        "internalType": "uint16"
      }
    ],
    "outputs": [],
    "stateMutability": "nonpayable"
  },
  {
    "type": "function",
    "name": "removeIdentityFromStorage",
    "inputs": [
      {
        "name": "_userAddress",
        "type": "address",
        "internalType": "address"
      }
    ],
    "outputs": [],
    "stateMutability": "nonpayable"
  },
  {
    "type": "function",
    "name": "storedIdentity",
    "inputs": [
      {
        "name": "_userAddress",
        "type": "address",
        "internalType": "address"
      }
    ],
    "outputs": [
      {
        "name": "",
        "type": "address",
        "internalType": "contract IIdentity"
      }
    ],
    "stateMutability": "view"
  },
  {
    "type": "function",
    "name": "storedInvestorCountry",
    "inputs": [
      {
        "name": "_userAddress",
        "type": "address",
        "internalType": "address"
      }
    ],
    "outputs": [
      {
        "name": "",
        "type": "uint16",
        "internalType": "uint16"
      }
    ],
    "stateMutability": "view"
  },
  {
    "type": "function",
    "name": "unbindIdentityRegistry",
    "inputs": [
      {
        "name": "_identityRegistry",
        "type": "address",
        "internalType": "address"
      }
    ],
    "outputs": [],
    "stateMutability": "nonpayable"
  },
  {
    "type": "event",
    "name": "CountryModified",
    "inputs": [
      {
        "name": "investorAddress",
        "type": "address",
        "indexed": true,
        "internalType": "address"
      },
      {
        "name": "country",
        "type": "uint16",
        "indexed": true,
        "internalType": "uint16"
      }
    ],
    "anonymous": false
  },
  {
    "type": "event",
    "name": "IdentityModified",
    "inputs": [
      {
        "name": "oldIdentity",
        "type": "address",
        "indexed": true,
        "internalType": "contract IIdentity"
      },
      {
        "name": "newIdentity",
        "type": "address",
        "indexed": true,
        "internalType": "contract IIdentity"
      }
    ],
    "anonymous": false
  },
  {
    "type": "event",
    "name": "IdentityRegistryBound",
    "inputs": [
      {
        "name": "identityRegistry",
        "type": "address",
        "indexed": true,
        "internalType": "address"
      }
    ],
    "anonymous": false
  },
  {
    "type": "event",
    "name": "IdentityRegistryUnbound",
    "inputs": [
      {
        "name": "identityRegistry",
        "type": "address",
        "indexed": true,
        "internalType": "address"
      }
    ],
    "anonymous": false
  },
  {
    "type": "event",
    "name": "IdentityStored",
    "inputs": [
      {
        "name": "investorAddress",
        "type": "address",
        "indexed": true,
        "internalType": "address"
      },
      {
        "name": "identity",
        "type": "address",
        "indexed": true,
        "internalType": "contract IIdentity"
      }
    ],
    "anonymous": false
  },
  {
    "type": "event",
    "name": "IdentityUnstored",
    "inputs": [
      {
        "name": "investorAddress",
        "type": "address",
        "indexed": true,
        "internalType": "address"
      },
      {
        "name": "identity",
        "type": "address",
        "indexed": true,
        "internalType": "contract IIdentity"
      }
    ],
    "anonymous": false
  }
]
